ImageButler-0.0.4.dist-info/DESCRIPTION.rst
ImageButler-0.0.4.dist-info/METADATA
ImageButler-0.0.4.dist-info/RECORD
ImageButler-0.0.4.dist-info/WHEEL
ImageButler-0.0.4.dist-info/entry_points.txt
ImageButler-0.0.4.dist-info/metadata.json
ImageButler-0.0.4.dist-info/top_level.txt
imagebutler/__init__.py
imagebutler/commands.py
imagebutler/imagebutler.py
imagebutler/job_workers.py
imagebutler/models.py
imagebutler/serving_objects.py
imagebutler/settings.py
imagebutler/types.py
imagebutler/utils.py
imagebutler/views.py
imagebutler/apis/__init__.py
imagebutler/apis/apis.py
imagebutler/apis/image.py
imagebutler/apis/images.py
imagebutler/apis/ping.py
imagebutler/commands/__init__.py
imagebutler/commands/image.py
imagebutler/commands/user.py
