Metadata-Version: 2.0
Name: ImageButler
Version: 0.0.4
Summary: Simple images serving service,
Home-page: https://viisix.space/projects/image-butler/
Author: Trong-Nghia Nguyen
Author-email: nghia@viisix.space
License: UNKNOWN
Platform: UNKNOWN
Classifier: Development Status :: 2 - Pre-Alpha
Classifier: Environment :: Console
Classifier: Environment :: Web Environment
Classifier: Framework :: Flask
Classifier: Intended Audience :: Developers
Classifier: License :: OSI Approved :: BSD License
Classifier: Operating System :: Unix
Classifier: Programming Language :: Python :: 3.6
Requires-Dist: Flask
Requires-Dist: Flask-Cors
Requires-Dist: Flask-Restful
Requires-Dist: Flask-SQLAlchemy
Requires-Dist: Flask-Migrate
Requires-Dist: Flask-Redislite
Requires-Dist: Flask-Login
Requires-Dist: pycrypto
Requires-Dist: Pillow
Requires-Dist: progressbar2
Requires-Dist: piexif
